ape/core/__init__.py
ape/core/core_prompts/__init__.py
ape/core/core_prompts/dataset-descriptor-with-prior-observations.prompt
ape/core/core_prompts/dataset-descriptor.prompt
ape/core/core_prompts/describe-prompt.prompt
ape/core/core_prompts/evoprompt-prompt-de.prompt
ape/core/core_prompts/evoprompt-prompt-ga.prompt
ape/core/core_prompts/evoprompt-prompt-para.prompt
ape/core/core_prompts/expel-failure-feedback-generator.prompt
ape/core/core_prompts/expel-feedback-applier.prompt
ape/core/core_prompts/expel-success-feedback-generator.prompt
ape/core/core_prompts/gen-fewshot-placeholder.prompt
ape/core/core_prompts/gen-instruction-seeds.prompt
ape/core/core_prompts/gen-instruction-with-eval.prompt
ape/core/core_prompts/gen-instructions.prompt
ape/core/core_prompts/gen-merged-prompt.prompt
ape/core/core_prompts/gen-metric-description-with-global-metric.prompt
ape/core/core_prompts/gen-metric-description.prompt
ape/core/core_prompts/observation-summarizer.prompt
ape/core/core_prompts/reformat-prompt-json-object.prompt
ape/core/core_prompts/reformat-prompt-json-schema.prompt
ape/core/core_prompts/text-grad-evo-applier.prompt
ape/core/core_prompts/text-grad-evo-generator.prompt
ape/core/core_prompts/text-gradient-applier.prompt
ape/core/core_prompts/text-gradient-generator.prompt
ape/core/trainer/__init__.py
ape/core/trainer/base.py
ape/core/trainer/community/EXAMPLE_README.md
ape/core/trainer/community/expel/README.md
ape/core/trainer/community/expel/expel_trainer.py
ape/core/trainer/community/few_shot/README.md
ape/core/trainer/community/few_shot/fewshot_trainer.py
ape/core/trainer/community/optuna/README.md
ape/core/trainer/community/optuna/optuna_trainer.py
ape/core/trainer/community/text_grad_evo/README.md
ape/core/trainer/community/text_grad_evo/text_grad_evo_trainer.py
ape/core/trainer/community/text_gradient/README.md
ape/core/trainer/community/text_gradient/text_gradient_trainer.py
ape/core/trainer/papers/EXAMPLE_README.md
ape_core-0.10.0.dist-info/METADATA
ape_core-0.10.0.dist-info/WHEEL
ape_core-0.10.0.dist-info/top_level.txt
ape_core-0.10.0.dist-info/RECORD
