Metadata-Version: 2.1
Name: ape-core
Version: 0.10.0
Summary: Ape: your AI prompt engineer
Author-email: weavel <founders@weavel.ai>
License: MIT
Project-URL: Homepage, https://github.com/weavel-ai/Ape/tree/main/libs/core
Project-URL: Bug Tracker, https://github.com/weavel-ai/Ape/issues
Keywords: prompt,prompt engineering,AI prompt engineer,llm
Classifier: Programming Language :: Python :: 3
Classifier: License :: OSI Approved :: MIT License
Classifier: Operating System :: OS Independent
Requires-Python: >=3.10
Requires-Dist: ape-common<0.3.0,>=0.2.0
Requires-Dist: optuna<5.0.0,>=4.0.0
Requires-Dist: psycopg2-binary<3.0.0,>=2.9.9
Requires-Dist: sqlalchemy<3.0.0,>=2.0.35
Requires-Dist: nest-asyncio<2.0.0,>=1.6.0
Provides-Extra: dev
Requires-Dist: pytest; extra == "dev"
Requires-Dist: black; extra == "dev"
